[
  {
    "layer": "model.layers.54.self_attn.q_proj",
    "shape": [
      8192,
      8192
    ],
    "block_size": 4,
    "codebook_size": 256,
    "l_max": 6,
    "br_rmse": 0.041019607335329056,
    "rel_mse": 0.22472698986530304,
    "unique_programs": 3497056,
    "total_blocks": 4194304,
    "avg_depth": 4.520611763000488,
    "bps": 2.4218660377953163,
    "encode_time_s": 0.5232503051757813
  },
  {
    "layer": "model.layers.54.self_attn.q_proj",
    "shape": [
      8192,
      8192
    ],
    "block_size": 4,
    "codebook_size": 64,
    "l_max": 6,
    "br_rmse": 0.041019607335329056,
    "rel_mse": 0.269228458404541,
    "unique_programs": 3289313,
    "total_blocks": 4194304,
    "avg_depth": 4.892514228820801,
    "bps": 1.9962529921028724,
    "encode_time_s": 0.14409913635253907
  },
  {
    "layer": "model.layers.54.self_attn.q_proj",
    "shape": [
      8192,
      8192
    ],
    "block_size": 8,
    "codebook_size": 256,
    "l_max": 6,
    "br_rmse": 0.041019607335329056,
    "rel_mse": 0.5719190835952759,
    "unique_programs": 1035559,
    "total_blocks": 1048576,
    "avg_depth": 5.806439399719238,
    "bps": 0.7661949640386728,
    "encode_time_s": 0.10251216125488281
  },
  {
    "layer": "model.layers.0.self_attn.q_proj",
    "shape": [
      8192,
      8192
    ],
    "block_size": 4,
    "codebook_size": 256,
    "l_max": 6,
    "br_rmse": 0.0035287837963551283,
    "rel_mse": 0.0029571326449513435,
    "unique_programs": 1597356,
    "total_blocks": 4194304,
    "avg_depth": 3.7069754600524902,
    "bps": 2.0150478863213173,
    "encode_time_s": 0.32307672119140624
  },
  {
    "layer": "model.layers.0.self_attn.q_proj",
    "shape": [
      8192,
      8192
    ],
    "block_size": 4,
    "codebook_size": 64,
    "l_max": 6,
    "br_rmse": 0.0035287837963551283,
    "rel_mse": 0.04431159049272537,
    "unique_programs": 119484,
    "total_blocks": 4194304,
    "avg_depth": 2.978847026824951,
    "bps": 1.2786277913544288,
    "encode_time_s": 0.13276383972167968
  }
]