{
  "text_source": "raw",
  "runtime_mode": "adaptive-shadow",
  "layer_count": 560,
  "runtime_summary": {
    "local_palette_grouped": 2,
    "adaptive_global_id": 558
  },
  "grouped_local_layers": 2,
  "fused_global_layers": 0,
  "adaptive_global_layers": 558,
  "adaptive_state": {
    "validated_layers": 558,
    "fallback_layers": 6,
    "fallback_events": 6,
    "shadow_mismatch_layers": 0,
    "shadow_mismatch_events": 0,
    "primary_disabled_layers": 6
  },
  "routed": {
    "perplexity": 519364.60306074,
    "total_tokens": 3584,
    "num_windows": 4,
    "elapsed_s": 109.18881559371948,
    "tok_s": 32.82387468452539
  },
  "grouped_local_targets": [
    {
      "name": "model.layers.0.self_attn.q_proj",
      "group_rows": 8192,
      "group_cols": 8192
    },
    {
      "name": "model.layers.0.mlp.up_proj",
      "group_rows": 28672,
      "group_cols": 8192
    }
  ]
}