{
  "text_source": "raw",
  "num_windows": 16,
  "cache_max_mb": 128,
  "modes": [
    "baseline",
    "eager",
    "cached"
  ],
  "baseline": {
    "metrics": {
      "perplexity": 2.780532324100235,
      "total_tokens": 9728,
      "num_windows": 16,
      "elapsed_s": 8.955671548843384,
      "tok_s": 1086.2390326559444
    },
    "eval_vram": [
      {
        "device": 0,
        "allocated_mb": 44468.8,
        "reserved_mb": 45934.0,
        "peak_mb": 45178.8
      },
      {
        "device": 1,
        "allocated_mb": 45728.9,
        "reserved_mb": 46580.0,
        "peak_mb": 46385.9
      },
      {
        "device": 2,
        "allocated_mb": 44468.8,
        "reserved_mb": 47828.0,
        "peak_mb": 47214.8
      }
    ],
    "replace_vram": [
      {
        "device": 0,
        "allocated_mb": 44436.8,
        "reserved_mb": 44438.0,
        "peak_mb": 44436.8
      },
      {
        "device": 1,
        "allocated_mb": 45696.9,
        "reserved_mb": 45698.0,
        "peak_mb": 45696.9
      },
      {
        "device": 2,
        "allocated_mb": 44436.8,
        "reserved_mb": 44438.0,
        "peak_mb": 44436.8
      }
    ],
    "eval_peak_mb": 47214.8,
    "replace_peak_mb": 45696.9,
    "layer_stats_count": 0
  },
  "eager": {
    "metrics": {
      "perplexity": 2.7783993087362377,
      "total_tokens": 9728,
      "num_windows": 16,
      "elapsed_s": 13.086775302886963,
      "tok_s": 743.3458414964906
    },
    "eval_vram": [
      {
        "device": 0,
        "allocated_mb": 88052.9,
        "reserved_mb": 99248.0,
        "peak_mb": 94134.7
      },
      {
        "device": 1,
        "allocated_mb": 91424.9,
        "reserved_mb": 99058.0,
        "peak_mb": 92081.9
      },
      {
        "device": 2,
        "allocated_mb": 86900.8,
        "reserved_mb": 95176.0,
        "peak_mb": 89645.8
      }
    ],
    "replace_vram": [
      {
        "device": 0,
        "allocated_mb": 86900.9,
        "reserved_mb": 106240.0,
        "peak_mb": 98387.6
      },
      {
        "device": 1,
        "allocated_mb": 91424.9,
        "reserved_mb": 110232.0,
        "peak_mb": 102911.6
      },
      {
        "device": 2,
        "allocated_mb": 86900.8,
        "reserved_mb": 106240.0,
        "peak_mb": 98387.5
      }
    ],
    "eval_peak_mb": 94134.7,
    "replace_peak_mb": 102911.6,
    "layer_stats_count": 560
  },
  "cached": {
    "metrics": {
      "perplexity": 2.7756429443147277,
      "total_tokens": 9728,
      "num_windows": 16,
      "elapsed_s": 19.28721785545349,
      "tok_s": 504.37549225117465
    },
    "eval_vram": [
      {
        "device": 0,
        "allocated_mb": 95417.5,
        "reserved_mb": 99638.0,
        "peak_mb": 98106.6
      },
      {
        "device": 1,
        "allocated_mb": 99493.9,
        "reserved_mb": 103946.0,
        "peak_mb": 102166.9
      },
      {
        "device": 2,
        "allocated_mb": 94393.5,
        "reserved_mb": 100064.0,
        "peak_mb": 97138.5
      }
    ],
    "replace_vram": [
      {
        "device": 0,
        "allocated_mb": 86905.5,
        "reserved_mb": 106246.0,
        "peak_mb": 98392.2
      },
      {
        "device": 1,
        "allocated_mb": 91429.9,
        "reserved_mb": 107506.0,
        "peak_mb": 102916.6
      },
      {
        "device": 2,
        "allocated_mb": 86905.5,
        "reserved_mb": 103514.0,
        "peak_mb": 98392.2
      }
    ],
    "eval_peak_mb": 102166.9,
    "replace_peak_mb": 102916.6,
    "layer_stats_count": 560
  },
  "eager_vs_baseline": {
    "ppl_gap": -0.002133015363997348,
    "tok_s_ratio": 0.6843298934664026,
    "peak_vram_delta_mb": 46919.899999999994
  },
  "cached_vs_baseline": {
    "ppl_gap": -0.004889379785507408,
    "tok_s_ratio": 0.4643319537302345,
    "peak_vram_delta_mb": 54952.09999999999
  }
}